mrkle-0.0.1rc0.dist-info/METADATA
mrkle-0.0.1rc0.dist-info/WHEEL
mrkle/__init__.py
mrkle/_mrkle_rs.abi3.so
mrkle/_proof/__init__.py
mrkle/_proof/__init__.pyi
mrkle/_tree/__init__.py
mrkle/_tree/__init__.pyi
mrkle/crypto/__init__.py
mrkle/crypto/__init__.pyi
mrkle/crypto/typing.py
mrkle/errors/__init__.py
mrkle/errors/__init__.pyi
mrkle/iter.py
mrkle/node.py
mrkle/py.typed
mrkle/tree.py
mrkle/typing.py
mrkle/utils.py
mrkle-0.0.1rc0.dist-info/RECORD
